Compiled from "Test.java"
public class Test {
  public final int dum;

  public java.lang.String test;

  public Test(java.lang.String);
    Code:
       0: aload_0
       1: invokespecial #1                  // Method java/lang/Object."<init>":()V
       4: aload_0
       5: aload_1
       6: putfield      #7                  // Field test:Ljava/lang/String;
       9: return

  private final java.lang.String getTest();
    Code:
       0: aload_0
       1: getfield      #7                  // Field test:Ljava/lang/String;
       4: areturn
}
